{
  "FrontOfficeCollection": {
    "doc1": {
      "category": "INTRODUCTION - TOURISM AND ITS IMPORTANCE",
      "order": 1,
      "subcategory": [
        {
          "name": "E-Learning",
          "link": "https://new-acc-space-2807.ispring.com/app/preview/6040e2c0-117d-11ef-ba88-8a12e27a05a8"
        },
        {
          "name": "Checking",
          "link": "https://firebasestorage.googleapis.com/v0/b/lite-learning-lab.appspot.com/o/Profluent%20English%2FSounds%20Animation%2FVowels%2FLong%20vowels%2FLong%20vowel%20u%20or%20u%3A%2FVowels%20u%CB%90%20Monophthongs.mp4?alt=media&token=a2321bb2-8bca-48f9-b831-680c4c1f0c2a"
        },
        {
          "name": "Checking",
          "link": "https://new-acc-space-2807.ispring.com/app/preview/b744c324-1288-11ee-9bc6-dec30c56cf91"
        }
      ]
    },
    "doc2": {
      "category": "INTRODUCTION - HOSPITALITY AND ITS ORIGIN",
      "order": 2,
      "subcategory": [
        {
          "name": "E-Learning",
          "link": "https://new-acc-space-2807.ispring.com/app/preview/6040e2c0-117d-11ef-ba88-8a12e27a05a8"
        },
        {
          "name": "Checking",
          "link": "https://firebasestorage.googleapis.com/v0/b/lite-learning-lab.appspot.com/o/Profluent%20English%2FSounds%20Animation%2FVowels%2FLong%20vowels%2FLong%20vowel%20u%20or%20u%3A%2FVowels%20u%CB%90%20Monophthongs.mp4?alt=media&token=a2321bb2-8bca-48f9-b831-680c4c1f0c2a"
        },
        {
          "name": "Checking",
          "link": "https://new-acc-space-2807.ispring.com/app/preview/b744c324-1288-11ee-9bc6-dec30c56cf91"
        }
      ]
    },
    "doc3": {
      "category": "INTRODUCTION - HOTELS, THEIR EVOLUTION AND GROWTH",
      "order": 3,
      "subcategory": [
        {
          "name": "E-Learning",
          "link": "https://new-acc-space-2807.ispring.com/app/preview/6040e2c0-117d-11ef-ba88-8a12e27a05a8"
        },
        {
          "name": "Checking",
          "link": "https://firebasestorage.googleapis.com/v0/b/lite-learning-lab.appspot.com/o/Profluent%20English%2FSounds%20Animation%2FVowels%2FLong%20vowels%2FLong%20vowel%20u%20or%20u%3A%2FVowels%20u%CB%90%20Monophthongs.mp4?alt=media&token=a2321bb2-8bca-48f9-b831-680c4c1f0c2a"
        },
        {
          "name": "Checking",
          "link": "https://new-acc-space-2807.ispring.com/app/preview/b744c324-1288-11ee-9bc6-dec30c56cf91"
        }
      ]
    },
    "doc4": {
      "category": "INTRODUCTION - CORE AREAS FRONT OFFICE",
      "order": 4,
      "subcategory": [
        {
          "name": "E-Learning",
          "link": "https://new-acc-space-2807.ispring.com/app/preview/6040e2c0-117d-11ef-ba88-8a12e27a05a8"
        },
        {
          "name": "Checking",
          "link": "https://firebasestorage.googleapis.com/v0/b/lite-learning-lab.appspot.com/o/Profluent%20English%2FSounds%20Animation%2FVowels%2FLong%20vowels%2FLong%20vowel%20u%20or%20u%3A%2FVowels%20u%CB%90%20Monophthongs.mp4?alt=media&token=a2321bb2-8bca-48f9-b831-680c4c1f0c2a"
        },
        {
          "name": "Checking",
          "link": "https://new-acc-space-2807.ispring.com/app/preview/b744c324-1288-11ee-9bc6-dec30c56cf91"
        }
      ]
    },
    "doc5": {
      "category": "INTRODUCTION - TRAVEL AND HOTEL INDUSTRY AND THEIR INTER-RELATIONSHIP",
      "order": 5,
      "subcategory": [
        {
          "name": "E-Learning",
          "link": "https://new-acc-space-2807.ispring.com/app/preview/6040e2c0-117d-11ef-ba88-8a12e27a05a8"
        },
        {
          "name": "Checking",
          "link": "https://firebasestorage.googleapis.com/v0/b/lite-learning-lab.appspot.com/o/Profluent%20English%2FSounds%20Animation%2FVowels%2FLong%20vowels%2FLong%20vowel%20u%20or%20u%3A%2FVowels%20u%CB%90%20Monophthongs.mp4?alt=media&token=a2321bb2-8bca-48f9-b831-680c4c1f0c2a"
        },
        {
          "name": "Checking",
          "link": "https://new-acc-space-2807.ispring.com/app/preview/b744c324-1288-11ee-9bc6-dec30c56cf91"
        }
      ]
    },
    "doc6": {
      "category": "INTRODUCTION - INTERDEPENDENCY OF TOURISM, TRAVEL, AND HOSPITALITY INDUSTRY",
      "order": 6,
      "subcategory": [
        {
          "name": "E-Learning",
          "link": "https://new-acc-space-2807.ispring.com/app/preview/6040e2c0-117d-11ef-ba88-8a12e27a05a8"
        },
        {
          "name": "Checking",
          "link": "https://firebasestorage.googleapis.com/v0/b/lite-learning-lab.appspot.com/o/Profluent%20English%2FSounds%20Animation%2FVowels%2FLong%20vowels%2FLong%20vowel%20u%20or%20u%3A%2FVowels%20u%CB%90%20Monophthongs.mp4?alt=media&token=a2321bb2-8bca-48f9-b831-680c4c1f0c2a"
        },
        {
          "name": "Checking",
          "link": "https://new-acc-space-2807.ispring.com/app/preview/b744c324-1288-11ee-9bc6-dec30c56cf91"
        }
      ]
    },
    "doc7": {
      "category": "INTRODUCTION - CLASSIFICATION OF HOTELS",
      "order": 7,
      "subcategory": [
        {
          "name": "E-Learning",
          "link": "https://new-acc-space-2807.ispring.com/app/preview/6040e2c0-117d-11ef-ba88-8a12e27a05a8"
        },
        {
          "name": "Checking",
          "link": "https://firebasestorage.googleapis.com/v0/b/lite-learning-lab.appspot.com/o/Profluent%20English%2FSounds%20Animation%2FVowels%2FLong%20vowels%2FLong%20vowel%20u%20or%20u%3A%2FVowels%20u%CB%90%20Monophthongs.mp4?alt=media&token=a2321bb2-8bca-48f9-b831-680c4c1f0c2a"
        },
        {
          "name": "Checking",
          "link": "https://new-acc-space-2807.ispring.com/app/preview/b744c324-1288-11ee-9bc6-dec30c56cf91"
        }
      ]
    },
    "doc8": {
      "category": "STAFFING AND ORGANIZATIONAL STRUCTURE OF HOTEL",
      "order": 8,
      "subcategory": [
        {
          "name": "E-Learning",
          "link": "https://new-acc-space-2807.ispring.com/app/preview/6040e2c0-117d-11ef-ba88-8a12e27a05a8"
        },
        {
          "name": "Checking",
          "link": "https://firebasestorage.googleapis.com/v0/b/lite-learning-lab.appspot.com/o/Profluent%20English%2FSounds%20Animation%2FVowels%2FLong%20vowels%2FLong%20vowel%20u%20or%20u%3A%2FVowels%20u%CB%90%20Monophthongs.mp4?alt=media&token=a2321bb2-8bca-48f9-b831-680c4c1f0c2a"
        },
        {
          "name": "Checking",
          "link": "https://new-acc-space-2807.ispring.com/app/preview/b744c324-1288-11ee-9bc6-dec30c56cf91"
        }
      ]
    },
    "doc9": {
      "category": "FRONT OFFICE ORGANIZATION",
      "order": 9,
      "subcategory": [
        {
          "name": "E-Learning",
          "link": "https://new-acc-space-2807.ispring.com/app/preview/6040e2c0-117d-11ef-ba88-8a12e27a05a8"
        },
        {
          "name": "Checking",
          "link": "https://firebasestorage.googleapis.com/v0/b/lite-learning-lab.appspot.com/o/Profluent%20English%2FSounds%20Animation%2FVowels%2FLong%20vowels%2FLong%20vowel%20u%20or%20u%3A%2FVowels%20u%CB%90%20Monophthongs.mp4?alt=media&token=a2321bb2-8bca-48f9-b831-680c4c1f0c2a"
        },
        {
          "name": "Checking",
          "link": "https://new-acc-space-2807.ispring.com/app/preview/b744c324-1288-11ee-9bc6-dec30c56cf91"
        }
      ]
    },
    "doc10": {
      "category": "UPDATED FRONT OFFICE LAYOUT AND EQUIPMENT",
      "order": 10,
      "subcategory": [
        {
          "name": "E-Learning",
          "link": "https://new-acc-space-2807.ispring.com/app/preview/6040e2c0-117d-11ef-ba88-8a12e27a05a8"
        },
        {
          "name": "Checking",
          "link": "https://firebasestorage.googleapis.com/v0/b/lite-learning-lab.appspot.com/o/Profluent%20English%2FSounds%20Animation%2FVowels%2FLong%20vowels%2FLong%20vowel%20u%20or%20u%3A%2FVowels%20u%CB%90%20Monophthongs.mp4?alt=media&token=a2321bb2-8bca-48f9-b831-680c4c1f0c2a"
        },
        {
          "name": "Checking",
          "link": "https://new-acc-space-2807.ispring.com/app/preview/b744c324-1288-11ee-9bc6-dec30c56cf91"
        }
      ]
    },
    "doc11": {
      "category": "JOB DESCRIPTION OF FRONT OFFICE PERSONNEL",
      "order": 11,
      "subcategory": [
        {
          "name": "E-Learning",
          "link": "https://new-acc-space-2807.ispring.com/app/preview/6040e2c0-117d-11ef-ba88-8a12e27a05a8"
        },
        {
          "name": "Checking",
          "link": "https://firebasestorage.googleapis.com/v0/b/lite-learning-lab.appspot.com/o/Profluent%20English%2FSounds%20Animation%2FVowels%2FLong%20vowels%2FLong%20vowel%20u%20or%20u%3A%2FVowels%20u%CB%90%20Monophthongs.mp4?alt=media&token=a2321bb2-8bca-48f9-b831-680c4c1f0c2a"
        },
        {
          "name": "Checking",
          "link": "https://new-acc-space-2807.ispring.com/app/preview/b744c324-1288-11ee-9bc6-dec30c56cf91"
        }
      ]
    },
    "doc12": {
      "category": "ATTRIBUTES OF FRONT OFFICE STAFF",
      "order": 12,
      "subcategory": [
        {
          "name": "E-Learning",
          "link": "https://new-acc-space-2807.ispring.com/app/preview/6040e2c0-117d-11ef-ba88-8a12e27a05a8"
        },
        {
          "name": "Checking",
          "link": "https://firebasestorage.googleapis.com/v0/b/lite-learning-lab.appspot.com/o/Profluent%20English%2FSounds%20Animation%2FVowels%2FLong%20vowels%2FLong%20vowel%20u%20or%20u%3A%2FVowels%20u%CB%90%20Monophthongs.mp4?alt=media&token=a2321bb2-8bca-48f9-b831-680c4c1f0c2a"
        },
        {
          "name": "Checking",
          "link": "https://new-acc-space-2807.ispring.com/app/preview/b744c324-1288-11ee-9bc6-dec30c56cf91"
        }
      ]
    },
    "doc13": {
      "category": "GRE AND LOBBY MANAGER",
      "order": 13,
      "subcategory": [
        {
          "name": "E-Learning",
          "link": "https://new-acc-space-2807.ispring.com/app/preview/6040e2c0-117d-11ef-ba88-8a12e27a05a8"
        },
        {
          "name": "Checking",
          "link": "https://firebasestorage.googleapis.com/v0/b/lite-learning-lab.appspot.com/o/Profluent%20English%2FSounds%20Animation%2FVowels%2FLong%20vowels%2FLong%20vowel%20u%20or%20u%3A%2FVowels%20u%CB%90%20Monophthongs.mp4?alt=media&token=a2321bb2-8bca-48f9-b831-680c4c1f0c2a"
        },
        {
          "name": "Checking",
          "link": "https://new-acc-space-2807.ispring.com/app/preview/b744c324-1288-11ee-9bc6-dec30c56cf91"
        }
      ]
    },
    "doc14": {
      "category": "GUEST CYCLE",
      "order": 14,
      "subcategory": [
        {
          "name": "E-Learning",
          "link": "https://new-acc-space-2807.ispring.com/app/preview/6040e2c0-117d-11ef-ba88-8a12e27a05a8"
        },
        {
          "name": "Checking",
          "link": "https://firebasestorage.googleapis.com/v0/b/lite-learning-lab.appspot.com/o/Profluent%20English%2FSounds%20Animation%2FVowels%2FLong%20vowels%2FLong%20vowel%20u%20or%20u%3A%2FVowels%20u%CB%90%20Monophthongs.mp4?alt=media&token=a2321bb2-8bca-48f9-b831-680c4c1f0c2a"
        },
        {
          "name": "Checking",
          "link": "https://new-acc-space-2807.ispring.com/app/preview/b744c324-1288-11ee-9bc6-dec30c56cf91"
        }
      ]
    },
    "doc15": {
      "category": "TYPES OF HOTEL GUESTS",
      "order": 15,
      "subcategory": [
        {
          "name": "E-Learning",
          "link": "https://new-acc-space-2807.ispring.com/app/preview/6040e2c0-117d-11ef-ba88-8a12e27a05a8"
        },
        {
          "name": "Checking",
          "link": "https://firebasestorage.googleapis.com/v0/b/lite-learning-lab.appspot.com/o/Profluent%20English%2FSounds%20Animation%2FVowels%2FLong%20vowels%2FLong%20vowel%20u%20or%20u%3A%2FVowels%20u%CB%90%20Monophthongs.mp4?alt=media&token=a2321bb2-8bca-48f9-b831-680c4c1f0c2a"
        },
        {
          "name": "Checking",
          "link": "https://new-acc-space-2807.ispring.com/app/preview/b744c324-1288-11ee-9bc6-dec30c56cf91"
        }
      ]
    },
    "doc16": {
      "category": "RESERVATION",
      "order": 16,
      "subcategory": [
        {
          "name": "E-Learning",
          "link": "https://new-acc-space-2807.ispring.com/app/preview/6040e2c0-117d-11ef-ba88-8a12e27a05a8"
        },
        {
          "name": "Checking",
          "link": "https://firebasestorage.googleapis.com/v0/b/lite-learning-lab.appspot.com/o/Profluent%20English%2FSounds%20Animation%2FVowels%2FLong%20vowels%2FLong%20vowel%20u%20or%20u%3A%2FVowels%20u%CB%90%20Monophthongs.mp4?alt=media&token=a2321bb2-8bca-48f9-b831-680c4c1f0c2a"
        },
        {
          "name": "Checking",
          "link": "https://new-acc-space-2807.ispring.com/app/preview/b744c324-1288-11ee-9bc6-dec30c56cf91"
        }
      ]
    },
    "doc17": {
      "category": "GROUP RESERVATION AND CANCELLATIONS",
      "order": 17,
      "subcategory": [
        {
          "name": "E-Learning",
          "link": "https://new-acc-space-2807.ispring.com/app/preview/6040e2c0-117d-11ef-ba88-8a12e27a05a8"
        },
        {
          "name": "Checking",
          "link": "https://firebasestorage.googleapis.com/v0/b/lite-learning-lab.appspot.com/o/Profluent%20English%2FSounds%20Animation%2FVowels%2FLong%20vowels%2FLong%20vowel%20u%20or%20u%3A%2FVowels%20u%CB%90%20Monophthongs.mp4?alt=media&token=a2321bb2-8bca-48f9-b831-680c4c1f0c2a"
        },
        {
          "name": "Checking",
          "link": "https://new-acc-space-2807.ispring.com/app/preview/b744c324-1288-11ee-9bc6-dec30c56cf91"
        }
      ]
    },
    "doc18": {
      "category": "REGISTRATION",
      "order": 18,
      "subcategory": [
        {
          "name": "E-Learning",
          "link": "https://new-acc-space-2807.ispring.com/app/preview/6040e2c0-117d-11ef-ba88-8a12e27a05a8"
        },
        {
          "name": "Checking",
          "link": "https://firebasestorage.googleapis.com/v0/b/lite-learning-lab.appspot.com/o/Profluent%20English%2FSounds%20Animation%2FVowels%2FLong%20vowels%2FLong%20vowel%20u%20or%20u%3A%2FVowels%20u%CB%90%20Monophthongs.mp4?alt=media&token=a2321bb2-8bca-48f9-b831-680c4c1f0c2a"
        },
        {
          "name": "Checking",
          "link": "https://new-acc-space-2807.ispring.com/app/preview/b744c324-1288-11ee-9bc6-dec30c56cf91"
        }
      ]
    },
    "doc19": {
      "category": "FRONT OFFICE COMMUNICATION",
      "order": 19,
      "subcategory": [
        {
          "name": "E-Learning",
          "link": "https://new-acc-space-2807.ispring.com/app/preview/6040e2c0-117d-11ef-ba88-8a12e27a05a8"
        },
        {
          "name": "Checking",
          "link": "https://firebasestorage.googleapis.com/v0/b/lite-learning-lab.appspot.com/o/Profluent%20English%2FSounds%20Animation%2FVowels%2FLong%20vowels%2FLong%20vowel%20u%20or%20u%3A%2FVowels%20u%CB%90%20Monophthongs.mp4?alt=media&token=a2321bb2-8bca-48f9-b831-680c4c1f0c2a"
        },
        {
          "name": "Checking",
          "link": "https://new-acc-space-2807.ispring.com/app/preview/b744c324-1288-11ee-9bc6-dec30c56cf91"
        }
      ]
    },
    "doc20": {
      "category": "SECURITY DEPARTMENT",
      "order": 20,
      "subcategory": [
        {
          "name": "E-Learning",
          "link": "https://new-acc-space-2807.ispring.com/app/preview/6040e2c0-117d-11ef-ba88-8a12e27a05a8"
        },
        {
          "name": "Checking",
          "link": "https://firebasestorage.googleapis.com/v0/b/lite-learning-lab.appspot.com/o/Profluent%20English%2FSounds%20Animation%2FVowels%2FLong%20vowels%2FLong%20vowel%20u%20or%20u%3A%2FVowels%20u%CB%90%20Monophthongs.mp4?alt=media&token=a2321bb2-8bca-48f9-b831-680c4c1f0c2a"
        },
        {
          "name": "Checking",
          "link": "https://new-acc-space-2807.ispring.com/app/preview/b744c324-1288-11ee-9bc6-dec30c56cf91"
        }
      ]
    }
  }
}